{
  "clubs": [
    {
      "name": "Arsenal",
      "rank": 1,
      "played": 30,
      "won": 20,
      "lost": 5,
      "drawn": 5,
      "goal_diff": 45,
      "points": 65
    },
    {
      "name": "Liverpool",
      "rank": 2,
      "played": 30,
      "won": 18,
      "lost": 6,
      "drawn": 6,
      "goal_diff": 38,
      "points": 60
    },
    {
      "name": "Manchester City",
      "rank": 3,
      "played": 30,
      "won": 18,
      "lost": 7,
      "drawn": 5,
      "goal_diff": 42,
      "points": 59
    },
    {
      "name": "Aston Villa",
      "rank": 4,
      "played": 30,
      "won": 17,
      "lost": 7,
      "drawn": 6,
      "goal_diff": 20,
      "points": 57
    },
    {
      "name": "Tottenham",
      "rank": 5,
      "played": 30,
      "won": 15,
      "lost": 8,
      "drawn": 7,
      "goal_diff": 15,
      "points": 52
    },
    {
      "name": "Newcastle",
      "rank": 6,
      "played": 30,
      "won": 12,
      "lost": 10,
      "drawn": 8,
      "goal_diff": 10,
      "points": 44
    },
    {
      "name": "Man United",
      "rank": 7,
      "played": 30,
      "won": 11,
      "lost": 11,
      "drawn": 8,
      "goal_diff": 3,
      "points": 41
    },
    {
      "name": "West Ham",
      "rank": 8,
      "played": 30,
      "won": 10,
      "lost": 12,
      "drawn": 8,
      "goal_diff": -5,
      "points": 38
    },
    {
      "name": "Chelsea",
      "rank": 9,
      "played": 30,
      "won": 9,
      "lost": 13,
      "drawn": 8,
      "goal_diff": -4,
      "points": 35
    },
    {
      "name": "Brighton",
      "rank": 10,
      "played": 30,
      "won": 8,
      "lost": 14,
      "drawn": 8,
      "goal_diff": -8,
      "points": 32
    }
  ],
  "fixtures": [
    {
      "homeTeam": "Arsenal",
      "awayTeam": "Liverpool",
      "date": "2024-05-01",
      "time": "15:00",
      "result": "1-1"
    },
    {
      "homeTeam": "Manchester City",
      "awayTeam": "Chelsea",
      "date": "2024-05-02",
      "time": "18:00",
      "result": "2-0"
    }
  ],
  "topScorers": [
    {
      "name": "Erling Haaland",
      "team": "Manchester City",
      "goals": 22
    },
    {
      "name": "Mohamed Salah",
      "team": "Liverpool",
      "goals": 18
    },
    {
      "name": "Harry Kane",
      "team": "Tottenham",
      "goals": 16
    },
    {
      "name": "Bruno Fernandes",
      "team": "Man United",
      "goals": 15
    },
    {
      "name": "Dominic Calvert-Lewin",
      "team": "Everton",
      "goals": 14
    },
    {
      "name": "Sadio Mane",
      "team": "Liverpool",
      "goals": 13
    },
    {
      "name": "Jamie Vardy",
      "team": "Leicester City",
      "goals": 12
    },
    {
      "name": "Raheem Sterling",
      "team": "Manchester City",
      "goals": 11
    },
    {
      "name": "Patrick Bamford",
      "team": "Leeds United",
      "goals": 10
    },
    {
      "name": "Wilfried Zaha",
      "team": "Crystal Palace",
      "goals": 9
    },
    {
      "name": "Son Heung-min",
      "team": "Tottenham",
      "goals": 9
    }
  ]
}